smartmeter_datacollector_configurator/__init__.py
smartmeter_datacollector_configurator/__main__.py
smartmeter_datacollector_configurator/app.py
smartmeter_datacollector_configurator/authentication.py
smartmeter_datacollector_configurator/configurator.py
smartmeter_datacollector_configurator/dto.py
smartmeter_datacollector_configurator/static/css/app.28b3ec25.css
smartmeter_datacollector_configurator/static/css/chunk-vendors.2aefe66e.css
smartmeter_datacollector_configurator/static/favicon.ico
smartmeter_datacollector_configurator/static/fonts/fa-solid-900.0c6bfc66.eot
smartmeter_datacollector_configurator/static/fonts/fa-solid-900.b9625119.ttf
smartmeter_datacollector_configurator/static/fonts/fa-solid-900.d745348d.woff
smartmeter_datacollector_configurator/static/fonts/fa-solid-900.d824df7e.woff2
smartmeter_datacollector_configurator/static/img/fa-solid-900.37bc7099.svg
smartmeter_datacollector_configurator/static/index.html
smartmeter_datacollector_configurator/static/js/app.a8a51363.js
smartmeter_datacollector_configurator/static/js/app.a8a51363.js.map
smartmeter_datacollector_configurator/static/js/chunk-vendors.d815194d.js
smartmeter_datacollector_configurator/static/js/chunk-vendors.d815194d.js.map
smartmeter_datacollector_configurator/system.py
smartmeter_datacollector_configurator-1.3.0.dist-info/LICENSE
smartmeter_datacollector_configurator-1.3.0.dist-info/METADATA
smartmeter_datacollector_configurator-1.3.0.dist-info/WHEEL
smartmeter_datacollector_configurator-1.3.0.dist-info/entry_points.txt
smartmeter_datacollector_configurator-1.3.0.dist-info/RECORD
