Metadata-Version: 2.3
Name: smartmeter-datacollector-configurator
Version: 1.3.0
Summary: Smart Meter Data Collector Configurator
License: BSD-3-Clause
Author: Supercomputing Systems AG
Author-email: info@scs.ch
Maintainer: Supercomputing Systems AG
Maintainer-email: info@scs.ch
Requires-Python: >=3.10,<4.0
Classifier: Development Status :: 5 - Production/Stable
Classifier: License :: OSI Approved :: BSD License
Classifier: Programming Language :: Python :: 3
Classifier: Programming Language :: Python :: 3.10
Classifier: Programming Language :: Python :: 3.11
Classifier: Programming Language :: Python :: 3.12
Classifier: Programming Language :: Python :: 3.13
Classifier: Programming Language :: Python :: 3.14
Classifier: Typing :: Typed
Requires-Dist: pydantic (>=1.10.7,<1.11.0)
Requires-Dist: starlette (>=0.37.2,<0.38.0)
Requires-Dist: uvicorn (>=0.29.0,<0.30.0)
Project-URL: Bug Reports, https://github.com/scs/smartmeter-datacollector-configurator/issues
Project-URL: Documentation, https://github.com/scs/smartmeter-datacollector/wiki
Project-URL: Homepage, https://github.com/scs/smartmeter-datacollector-configurator
Project-URL: Pull Requests, https://github.com/scs/smartmeter-datacollector-configurator/pulls
Project-URL: Repository, https://github.com/scs/smartmeter-datacollector-configurator
Project-URL: SCS, https://www.scs.ch
